LICENSE
MANIFEST.in
README
setup.py
speaklater.py
quokka_speaklater.egg-info/PKG-INFO
quokka_speaklater.egg-info/SOURCES.txt
quokka_speaklater.egg-info/dependency_links.txt
quokka_speaklater.egg-info/not-zip-safe
quokka_speaklater.egg-info/top_level.txt