Metadata-Version: 1.1
Name: quokka-speaklater
Version: 1.3.1
Summary: Fork of implements a lazy string for python useful for use with gettext
Home-page: http://github.com/mitsuhiko/speaklater
Author: Armin Ronacher
Author-email: armin.ronacher@active-4.com
License: UNKNOWN
Platform: UNKNOWN
Classifier: Development Status :: 5 - Production/Stable
Classifier: License :: OSI Approved :: BSD License
Classifier: Topic :: Software Development :: Internationalization
Classifier: Programming Language :: Python
